MANIFEST.in
setup.py
./__init__.py
./__openerp__.py
data/account_chart.xml
data/account_tax.xml
data/account_tax_code.xml
data/l10n_chart_mx_wizard.xml
openerp_l10n_co.egg-info/PKG-INFO
openerp_l10n_co.egg-info/SOURCES.txt
openerp_l10n_co.egg-info/dependency_links.txt
openerp_l10n_co.egg-info/requires.txt
openerp_l10n_co.egg-info/top_level.txt
static/src/img/icon.png